kaibu_geojson_utils/VERSION
kaibu_geojson_utils/__init__.py
kaibu_geojson_utils-0.1.5.dist-info/LICENSE
kaibu_geojson_utils-0.1.5.dist-info/METADATA
kaibu_geojson_utils-0.1.5.dist-info/WHEEL
kaibu_geojson_utils-0.1.5.dist-info/top_level.txt
kaibu_geojson_utils-0.1.5.dist-info/RECORD
