Metadata-Version: 2.1
Name: kaibu-geojson-utils
Version: 0.1.5
Summary: A set of utility functions for working with GeoJSON annotations in [Kaibu](https://kaibu.org).
Home-page: https://github.com/imjoy-team/kaibu-geojson-utils
Author: ImJoy-Team
Author-email: imjoy.team@gmail.com
License: MIT
Platform: UNKNOWN
Classifier: Development Status :: 3 - Alpha
Classifier: Environment :: Web Environment
Classifier: Intended Audience :: Developers
Classifier: License :: OSI Approved :: MIT License
Classifier: Operating System :: OS Independent
Classifier: Programming Language :: Python
Classifier: Programming Language :: Python :: 3.7
Classifier: Programming Language :: Python :: 3.8
Classifier: Programming Language :: Python :: 3.9
Classifier: Programming Language :: Python :: 3.10
Classifier: Topic :: Internet
Requires-Python: >=3.7
License-File: LICENSE
Requires-Dist: Pillow
Requires-Dist: geojson
Requires-Dist: scikit-image
